pyram/__init__.py
pyram/decorators.py
pyram/ram.py
tests/__init__.py
pyram_sa-0.0.4.dist-info/LICENSE
pyram_sa-0.0.4.dist-info/METADATA
pyram_sa-0.0.4.dist-info/WHEEL
pyram_sa-0.0.4.dist-info/top_level.txt
pyram_sa-0.0.4.dist-info/RECORD
