Metadata-Version: 2.1
Name: pyram-sa
Version: 0.0.4
Summary: A Python client for RAM web services
Home-page: https://github.com/kehtra/PyRAM
Author: Jordy Chetty
Author-email: jxrrdy@gmail.com
License: UNKNOWN
Platform: UNKNOWN
Classifier: Programming Language :: Python :: 3
Classifier: License :: OSI Approved :: MIT License
Classifier: Operating System :: OS Independent
Requires-Python: >=3.6
Requires-Dist: zeep
